groupbytime/__init__.py
groupbytime/groupbytime.py
groupbytime-0.3.2.dist-info/DESCRIPTION.rst
groupbytime-0.3.2.dist-info/LICENSE.txt
groupbytime-0.3.2.dist-info/METADATA
groupbytime-0.3.2.dist-info/RECORD
groupbytime-0.3.2.dist-info/WHEEL
groupbytime-0.3.2.dist-info/metadata.json
groupbytime-0.3.2.dist-info/top_level.txt
