Metadata-Version: 2.0
Name: groupbytime
Version: 0.3.2
Summary: Convenience functions for grouping datetimes in pandas
Home-page: https://github.com/daviskirk/groupbytime
Author: Davis Kirkendall
Author-email: davis.e.kirkendall@gmail.com
License: MIT
Keywords: pandas groupby datetime timestamp
Platform: UNKNOWN
Classifier: Development Status :: 3 - Alpha
Classifier: Intended Audience :: Developers
Classifier: Topic :: Scientific/Engineering
Classifier: License :: OSI Approved :: MIT License
Classifier: Programming Language :: Python :: 3.3
Classifier: Programming Language :: Python :: 3.4
Classifier: Programming Language :: Python :: 3.5
Classifier: Programming Language :: Python :: 3.6
Requires-Dist: pandas
Provides-Extra: test
Requires-Dist: pytest; extra == 'test'
